{"is_source_file": true, "format": "JavaScript (React JSX)", "description": "React functional component named Header that displays a page header with title, subtitle, and user avatar.", "external_files": [], "external_methods": [], "published": ["Header"], "classes": [], "methods": [{"name": "Header({ title = 'Foodgo', subtitle = 'Order your favourite food!', avatarSrc = '' })", "description": "Functional React component displaying header information with props for title, subtitle, and avatar source.", "scope": "", "scopeKind": ""}], "calls": ["React", "React.createElement", "React JSX syntax"], "search-terms": ["Header", "React functional component", "title", "subtitle", "avatarSrc", "jsx", "public interface"], "state": 2, "file_id": 15, "knowledge_revision": 31, "git_revision": "", "ctags": [{"_type": "tag", "name": "Header", "path": "/home/kavia/workspace/code-generation/food-explorer-139177-139186/food_frontend/src/components/Header.js", "pattern": "/^export default function Header({ title = 'Foodgo', subtitle = 'Order your favourite food!', avat/", "language": "JavaScript", "kind": "function", "signature": "({ title = 'Foodgo', subtitle = 'Order your favourite food!', avatarSrc = '' })"}], "hash": "e034310ca834eacc5e57f72ec6eead67", "format-version": 4, "code-base-name": "food_frontend", "filename": "food_frontend/src/components/Header.js", "revision_history": [{"31": ""}]}